{
    "Training":"Active_examples/DoubleStimuli/train",
    "Test":"Active_examples/DoubleStimuli/test",
    "Exp_Info":{
        "Display_Type":"2D",
        "ThreeD_Type":"LeftRight",
        "Score_Levels":5,
        "Score_Names":[
            "Please Rate the Quality"
        ],
        "Score_Definition":[
            ["5. Imperceptible",
            "4. Perceptible but not annoying",
            "3. Slightly Annoying",
            "2. Annoying",
            "1. Very Annoying"]
        ],
        "View_Changing":"Active",
        "Refocusing":"None",
        "Comparison":"DoubleStimulus",
        "Save_Format":"Excel",
        "Skip_Preprocessing": true,
        "Two_Folder_Mode": true
    }
}